shafaratoolkit/__init__.py
shafaratoolkit/props.py
shafaratoolkit/pytorchtools.py
shafara_tool_kit-0.2.2.dist-info/LICENSE
shafara_tool_kit-0.2.2.dist-info/METADATA
shafara_tool_kit-0.2.2.dist-info/WHEEL
shafara_tool_kit-0.2.2.dist-info/RECORD
