Metadata-Version: 2.1
Name: shafara-tool-kit
Version: 0.2.2
Summary: 
Author: jumashafara
Author-email: jumashafara0@gmail.com
Requires-Python: >=3.9
Classifier: Programming Language :: Python :: 3
Classifier: Programming Language :: Python :: 3.9
Classifier: Programming Language :: Python :: 3.10
Classifier: Programming Language :: Python :: 3.11
